AUTHORS.rst
CONTRIBUTING.rst
HISTORY.rst
LICENSE
MANIFEST.in
README.rst
setup.cfg
setup.py
negative_i18n/__init__.py
negative_i18n/admin.py
negative_i18n/models.py
negative_i18n/trans_utils.py
negative_i18n/translation.py
negative_i18n.egg-info/PKG-INFO
negative_i18n.egg-info/SOURCES.txt
negative_i18n.egg-info/dependency_links.txt
negative_i18n.egg-info/not-zip-safe
negative_i18n.egg-info/requires.txt
negative_i18n.egg-info/top_level.txt
negative_i18n/migrations/0001_initial.py
negative_i18n/migrations/0002_auto_20190214_0850.py
negative_i18n/migrations/__init__.py
negative_i18n/old_crap/change_list_orig.html
negative_i18n/static/negative-i18n/negative-i18n-admin.css
negative_i18n/templates/negative-i18n/i18n_change_list.html
negative_i18n/templatetags/__init__.py
negative_i18n/templatetags/negative_i18n.py
negative_i18n/templatetags/negative_i18n_links.py
test/test_negative-i18n.py