Metadata-Version: 1.1
Name: negative-i18n
Version: 0.1.2
Summary: Database-stored translation strings for Django
Home-page: https://github.com/negative-space/negative-i18n
Author: Alex Rudakov
Author-email: ribozz@gmail.com
License: MIT
Keywords: negative-i18n
Platform: UNKNOWN
Classifier: Development Status :: 2 - Pre-Alpha
Classifier: Intended Audience :: Developers
Classifier: License :: OSI Approved :: MIT License
Classifier: Natural Language :: English
Classifier: Programming Language :: Python :: 3.6
Classifier: Programming Language :: Python :: Implementation :: PyPy
